{
  "articles": [
    {
      "id": "85596528",
      "filename": "20260302-0122-ekolohichni-tovary-dlya-sobak-stalyy-vybir-dlya-svidomykh-hospodariv.md",
      "title": "Екологічні товари для собак: сталий вибір для свідомих господарів",
      "summary": "Екологічні товари для собак стають все популярнішими серед свідомих господарів. Дізнайтесь, як ви можете зробити сталий вибір для свого улюбленого собаки.",
      "category": "інше",
      "image": "/images/generated/85596528.jpg",
      "created_at": "2026-03-02T01:22:32.068951+00:00"
    }
  ]
}