{
  "articles": [
    {
      "id": "cad2bb92",
      "filename": "20260225-0453-ukrayinskyy-pererobnyk-konopel-kurs-na-povnu-avtomatyzatsiyu-dorobky.md",
      "title": "Український переробник конопель: курс на повну автоматизацію доробки",
      "summary": "Компанія «АгроКонопля Інвест» оголосила про плани повністю механізувати післязбиральну доробку промислових конопель, інвестуючи в сучасні технології для підвищення ефективності та зниження ризиків.",
      "category": "бізнес",
      "image": "/images/generated/cad2bb92.jpg",
      "created_at": "2026-02-25T04:53:49.686051+00:00"
    }
  ]
}