{
  "articles": [
    {
      "id": "d4e8155d",
      "filename": "20260304-0638-maybutnye-konoplyanoyi-industriyi-pivnichnoyi-karoliny-vyklyky-ta-perspektyvy.md",
      "title": "Майбутнє конопляної індустрії Північної Кароліни: виклики та перспективи",
      "summary": "Північна Кароліна, колись лідер у вирощуванні промислових конопель, переживає значний спад. Фермери шукають нові ринки, а експерти вказують на необхідність розвитку переробки волокна та зерна для стабілізації галузі.",
      "category": "бізнес",
      "image": "/images/generated/d4e8155d.jpg",
      "created_at": "2026-03-04T06:38:53.168581+00:00"
    }
  ]
}